{
    "osd_0": {
        "28": {
            "messenger": [
                "1268827"
            ],
            "reactor": [
                "1268836"
            ]
        },
        "29": {
            "reactor": [
                "1268829",
                "1268840"
            ]
        },
        "30": {
            "reactor": [
                "1268830",
                "1268839"
            ]
        },
        "31": {
            "reactor": [
                "1268831",
                "1268843"
            ]
        },
        "32": {
            "reactor": [
                "1268832",
                "1268837"
            ]
        },
        "33": {
            "reactor": [
                "1268833",
                "1268842"
            ]
        },
        "34": {
            "reactor": [
                "1268834",
                "1268841"
            ]
        },
        "35": {
            "reactor": [
                "1268835",
                "1268838"
            ]
        }
    }
}